takeme/RsaUtil.py
takeme/TakemeClient.py
takeme/TakemeRequestor.py
takeme/__init__.py
takeme/templates/public.der
takeme_client_python-2.9.dist-info/METADATA
takeme_client_python-2.9.dist-info/WHEEL
takeme_client_python-2.9.dist-info/top_level.txt
takeme_client_python-2.9.dist-info/RECORD
