Metadata-Version: 2.1
Name: takeme-client-python
Version: 2.9
Summary: Python library for client who want to connect with takeme-service
Home-page: UNKNOWN
Author: Restravity (Ciputra Dhimas)
Author-email: <ciputra.developer@gmail.com>
License: UNKNOWN
Keywords: takeme,takeme client,python,takeme-client-python
Platform: UNKNOWN
Classifier: Development Status :: 1 - Planning
Classifier: Intended Audience :: Developers
Classifier: Programming Language :: Python :: 3
Classifier: Operating System :: Unix
Classifier: Operating System :: MacOS :: MacOS X
Classifier: Operating System :: Microsoft :: Windows
Requires-Dist: certifi
Requires-Dist: charset-normalizer
Requires-Dist: idna
Requires-Dist: pycryptodome
Requires-Dist: requestor
Requires-Dist: requests
Requires-Dist: unicode
Requires-Dist: urllib3
